json2ast/__init__.py
json2ast/node_map.py
json2ast-1.0.1.dist-info/LICENSE
json2ast-1.0.1.dist-info/METADATA
json2ast-1.0.1.dist-info/WHEEL
json2ast-1.0.1.dist-info/top_level.txt
json2ast-1.0.1.dist-info/RECORD
